DTRBench/__init__.py
DTRBench/core/__init__.py
DTRBench/core/base_hparams.py
DTRBench/core/base_obj.py
DTRBench/core/baseline_policy.py
DTRBench/core/helper_fn.py
DTRBench/core/logger.py
DTRBench/core/offpolicyRLHparams.py
DTRBench/core/offpolicyRLObj.py
DTRBench/core/policy.py
DTRBench/run_rl/__init__.py
DTRBench/run_rl/baseline_discrete.py
DTRBench/run_rl/online_continuous_baseline.py
DTRBench/run_rl/online_continuous_retrain.py
DTRBench/run_rl/online_continuous_search.py
DTRBench/run_rl/online_discrete_retrain.py
DTRBench/run_rl/online_discrete_search.py
DTRBench/utils/__init__.py
DTRBench/utils/data.py
DTRBench/utils/get_policy.py
DTRBench/utils/misc.py
DTRBench/utils/network.py
DTRBench/utils/parse_result_fn.py
DTRBench/utils/tile_coding.py
DTRBench/visual_fn/__init__.py
DTRBench/visual_fn/env_vis_fn.py
DTRBench/visual_fn/visual.py
DTR_Bench-0.1.0.dist-info/METADATA
DTR_Bench-0.1.0.dist-info/WHEEL
DTR_Bench-0.1.0.dist-info/top_level.txt
DTR_Bench-0.1.0.dist-info/RECORD
