Metadata-Version: 2.1
Name: DTR-Bench
Version: 0.1.0
Summary: DTR-Bench: An in silico Environment and Benchmark Platform for Reinforcement Learning Based Dynamic Treatment Regime
Author: Zhiyao Luo, Mingcheng Zhu
Author-email: zhiyao.luo@eng.ox.ac.uk
Requires-Dist: DTRGym
Requires-Dist: optuna ==3.2.0
Requires-Dist: wandb
